Metadata-Version: 2.1
Name: WSIPreToolkit
Version: 0.0.2
Summary: WSIPreToolkit is a python package that provides tools for enhancing medical images.
Home-page: https://github.com/Manas1820/WSIPreToolkit
Download-URL: https://github.com/Manas1820/WSIPreToolkit/archive/refs/tags/v0.0.2.tar.gz
Author: Manas Gupta
Author-email: manasgupta1820@gmail.com
License: MIT
Project-URL: Bug Tracker, https://github.com/Manas1820/WSIPreToolkit/issues
Keywords: pypi,WSI,medical
Classifier: Development Status :: 3 - Alpha
Classifier: Intended Audience :: Developers
Classifier: Topic :: Software Development :: Documentation
Classifier: License :: OSI Approved :: MIT License
Classifier: Programming Language :: Python :: 3
Classifier: Programming Language :: Python :: 3.7
Classifier: Programming Language :: Python :: 3.8
Classifier: Programming Language :: Python :: 3.9
License-File: LICENSE
